rowan_mcp/__init__.py
rowan_mcp/__main__.py
rowan_mcp/server.py
rowan_mcp/functions_v2/BENCHMARK.md
rowan_mcp/functions_v2/molecule_lookup.py
rowan_mcp/functions_v2/protein_management.py
rowan_mcp/functions_v2/submit_admet_workflow.py
rowan_mcp/functions_v2/submit_basic_calculation_workflow.py
rowan_mcp/functions_v2/submit_batch_docking_workflow.py
rowan_mcp/functions_v2/submit_batch_workflow.py
rowan_mcp/functions_v2/submit_bde_workflow.py
rowan_mcp/functions_v2/submit_conformer_search_workflow.py
rowan_mcp/functions_v2/submit_conformers_workflow.py
rowan_mcp/functions_v2/submit_descriptors_workflow.py
rowan_mcp/functions_v2/submit_docking_workflow.py
rowan_mcp/functions_v2/submit_double_ended_ts_search_workflow.py
rowan_mcp/functions_v2/submit_fukui_workflow.py
rowan_mcp/functions_v2/submit_hydrogen_bond_basicity_workflow.py
rowan_mcp/functions_v2/submit_ion_mobility_workflow.py
rowan_mcp/functions_v2/submit_irc_workflow.py
rowan_mcp/functions_v2/submit_macropka_workflow.py
rowan_mcp/functions_v2/submit_msa_workflow.py
rowan_mcp/functions_v2/submit_multistage_opt_workflow.py
rowan_mcp/functions_v2/submit_pka_workflow.py
rowan_mcp/functions_v2/submit_pose_analysis_md_workflow.py
rowan_mcp/functions_v2/submit_protein_cofolding_workflow.py
rowan_mcp/functions_v2/submit_redox_potential_workflow.py
rowan_mcp/functions_v2/submit_scan_workflow.py
rowan_mcp/functions_v2/submit_solubility_workflow.py
rowan_mcp/functions_v2/submit_spin_states_workflow.py
rowan_mcp/functions_v2/submit_strain_workflow.py
rowan_mcp/functions_v2/submit_tautomer_search_workflow.py
rowan_mcp/functions_v2/workflow_management_v2.py
rowan_mcp/tests/basic_calculation_from_json.py
rowan_mcp/tests/basic_calculation_with_constraint.py
rowan_mcp/tests/basic_calculation_with_solvent.py
rowan_mcp/tests/bde.py
rowan_mcp/tests/benchmark_queries.md
rowan_mcp/tests/cofolding_screen.py
rowan_mcp/tests/conformer_dependent_redox.py
rowan_mcp/tests/conformers.py
rowan_mcp/tests/data.json
rowan_mcp-2.3.2.dist-info/METADATA
rowan_mcp-2.3.2.dist-info/WHEEL
rowan_mcp-2.3.2.dist-info/entry_points.txt
rowan_mcp-2.3.2.dist-info/RECORD
