Metadata-Version: 2.4
Name: rowan-mcp
Version: 2.3.2
Summary: Model Context Protocol server for Rowan computational chemistry platform
Project-URL: Homepage, https://github.com/k-yenko/rowan-mcp
Author-email: Katherine Yenko <katherineayenko@gmail.com>
License: MIT
Classifier: Development Status :: 3 - Alpha
Classifier: Intended Audience :: Science/Research
Classifier: License :: OSI Approved :: MIT License
Classifier: Programming Language :: Python :: 3
Classifier: Programming Language :: Python :: 3.10
Classifier: Programming Language :: Python :: 3.11
Classifier: Programming Language :: Python :: 3.12
Classifier: Topic :: Scientific/Engineering :: Chemistry
Requires-Python: >=3.11
Requires-Dist: aiohttp>=3.12.15
Requires-Dist: fastapi>=0.104.0
Requires-Dist: fastmcp>=2.11.3
Requires-Dist: httpx>=0.25.0
Requires-Dist: mcp>=1.0.0
Requires-Dist: openai>=1.107.2
Requires-Dist: pubchempy>=1.0.4
Requires-Dist: pydantic>=2.0.0
Requires-Dist: python-dotenv>=1.0.0
Requires-Dist: rdkit>=2025.3.2
Requires-Dist: rowan-python>=2.1.9
Requires-Dist: stjames>=0.0.125
Requires-Dist: typing-extensions>=4.0.0
Requires-Dist: uvicorn>=0.24.0
Provides-Extra: dev
Requires-Dist: black>=23.0.0; extra == 'dev'
Requires-Dist: isort>=5.0.0; extra == 'dev'
Requires-Dist: mypy>=1.0.0; extra == 'dev'
Requires-Dist: pytest>=7.0.0; extra == 'dev'
